appointment/__init__.py
appointment/admin.py
appointment/apps.py
appointment/decorators.py
appointment/forms.py
appointment/logger_config.py
appointment/messages_.py
appointment/models.py
appointment/services.py
appointment/settings.py
appointment/tasks.py
appointment/urls.py
appointment/views.py
appointment/views_admin.py
appointment/email_sender/__init__.py
appointment/email_sender/email_sender.py
appointment/locale/fr/LC_MESSAGES/django.mo
appointment/locale/fr/LC_MESSAGES/django.po
appointment/static/css/appointments-user-details.css
appointment/static/css/appointments.css
appointment/static/css/appt-common.css
appointment/static/css/thank_you.css
appointment/static/css/verification_code.css
appointment/static/css/app_admin/admin.css
appointment/static/css/app_admin/btn.css
appointment/static/css/app_admin/days_off.css
appointment/static/css/app_admin/display_appointment.css
appointment/static/css/app_admin/service.css
appointment/static/css/app_admin/staff_member.css
appointment/static/css/app_admin/user_profile.css
appointment/static/css/app_admin/working_hours.css
appointment/static/img/email_hd_bg.jpg
appointment/static/js/appointments.js
appointment/static/js/js-utils.js
appointment/static/js/app_admin/staff_index.js
appointment/static/js/modal/error_modal.js
appointment/static/js/modal/show_modal.js
appointment/templates/administration/display_appointment.html
appointment/templates/administration/email_change_verification_code.html
appointment/templates/administration/manage_day_off.html
appointment/templates/administration/manage_service.html
appointment/templates/administration/manage_staff_member.html
appointment/templates/administration/manage_staff_personal_info.html
appointment/templates/administration/manage_working_hours.html
appointment/templates/administration/service_list.html
appointment/templates/administration/staff_index.html
appointment/templates/administration/staff_list.html
appointment/templates/administration/user_profile.html
django_appointment-3.9.2.dist-info/licenses/LICENSE
django_appointment-3.9.2.dist-info/METADATA
django_appointment-3.9.2.dist-info/WHEEL
django_appointment-3.9.2.dist-info/top_level.txt
django_appointment-3.9.2.dist-info/RECORD
