Metadata-Version: 2.4
Name: django-appointment
Version: 3.9.2
Summary: Managing appointment scheduling with customizable slots, staff features, and conflict handling.
Home-page: https://github.com/adamspd/django-appointment
Author: Adams Pierre David
Author-email: django-appt@adamspierredavid.com
License: Apache License 2.0
Project-URL: Author's Website, https://adamspierredavid.com/
Project-URL: Package's demo Website, https://django-appt.adamspierredavid.com/
Project-URL: Documentation, https://django-appt-doc.adamspierredavid.com/
Classifier: Development Status :: 5 - Production/Stable
Classifier: Intended Audience :: Developers
Classifier: License :: OSI Approved :: Apache Software License
Classifier: Framework :: Django
Classifier: Framework :: Django :: 4.2
Classifier: Programming Language :: Python
Classifier: Programming Language :: Python :: 3
Classifier: Programming Language :: Python :: 3 :: Only
Classifier: Programming Language :: Python :: 3.10
Classifier: Programming Language :: Python :: 3.11
Classifier: Operating System :: OS Independent
Classifier: Environment :: Web Environment
Classifier: Topic :: Internet :: WWW/HTTP
Classifier: Topic :: Internet :: WWW/HTTP :: Dynamic Content
Classifier: Topic :: Software Development :: Libraries :: Application Frameworks
Requires-Python: >=3.8
License-File: LICENSE
Requires-Dist: Django<6.0,>=4.2
Requires-Dist: Pillow<13.0,>=10.4
Requires-Dist: phonenumbers<10.0,>=8.13
Requires-Dist: django-phonenumber-field<9.0,>=8.0
Requires-Dist: babel<3.0,>=2.15
Requires-Dist: colorama<0.5,>=0.4
Requires-Dist: icalendar~=6.3.1
Dynamic: author
Dynamic: author-email
Dynamic: description
Dynamic: description-content-type
Dynamic: home-page
Dynamic: license-file
Dynamic: project-url
Dynamic: summary
